{"is_source_file": true, "format": "JavaScript (React JSX)", "description": "Main application component for Movie Explorer SPA; manages state, effects, and renders UI including search, movies grid, modals, and header/footer.", "external_files": ["./components/SearchBar", "./components/MovieGrid", "./components/LoadingSkeleton", "./components/EmptyState", "./components/ErrorBanner", "./components/MovieDetailModal", "./api/client.js", "./App.css", "./styles/theme.css", "./index.css"], "external_methods": ["searchMovies"], "published": ["App"], "classes": [], "methods": [{"name": "App()", "description": "Main React functional component that manages the movie search application, handles state, effects, and user interactions.", "scope": "", "scopeKind": ""}, {"name": "openDetails", "description": "Sets the selected movie to display in the details modal."}, {"name": "closeDetails", "description": "Clears the selected movie, closing the details modal."}, {"name": "run()", "scope": "App", "scopeKind": "function", "description": "unavailable"}], "calls": ["searchMovies(query || '')", "setQuery", "setMovies", "setStatus", "setErrorMsg", "setSelected", "process.env.REACT_APP_FEATURE_FLAGS", "JSON.parse", "new Date().getFullYear()"], "search-terms": ["React", "Movie Explorer", "useState", "useEffect", "useMemo", "Feature Flags", "searchMovies", "MovieGrid", "App component"], "state": 2, "file_id": 3, "knowledge_revision": 57, "git_revision": "eac3f6e7ede56ee51f341a26687743c34d7f17bf", "revision_history": [{"20": "eac3f6e7ede56ee51f341a26687743c34d7f17bf"}, {"53": "eac3f6e7ede56ee51f341a26687743c34d7f17bf"}, {"57": "eac3f6e7ede56ee51f341a26687743c34d7f17bf"}], "ctags": [{"_type": "tag", "name": "App", "path": "/home/kavia/workspace/code-generation/royal-movie-discover-222928-222938/movie_explorer_frontend/src/App.js", "pattern": "/^function App() {$/", "language": "JavaScript", "kind": "function", "signature": "()"}, {"_type": "tag", "name": "run", "path": "/home/kavia/workspace/code-generation/royal-movie-discover-222928-222938/movie_explorer_frontend/src/App.js", "pattern": "/^    async function run() {$/", "language": "JavaScript", "kind": "function", "signature": "()", "scope": "App", "scopeKind": "function"}], "hash": "c3ff71a1961f32950a20a44f61c374c0", "format-version": 4, "code-base-name": "movie_explorer_frontend", "filename": "movie_explorer_frontend/src/App.js"}